amulet/test_utils/_version.py
amulet/test_utils/amulet_test_utilsConfig.cmake
amulet/test_utils/py.typed
amulet/test_utils/test_utils.hpp
amulet_test_utils-1.3.1.dist-info/licenses/LICENSE
amulet_test_utils-1.3.1.dist-info/METADATA
amulet_test_utils-1.3.1.dist-info/WHEEL
amulet_test_utils-1.3.1.dist-info/top_level.txt
amulet_test_utils-1.3.1.dist-info/RECORD
