Metadata-Version: 2.4
Name: amulet-test-utils
Version: 1.3.1
Summary: A C++ test utility library.
Author: James Clare
Project-URL: Homepage, https://www.amuletmc.com
Project-URL: Repository, https://github.com/Amulet-Team/Amulet-Test-Utils
Project-URL: Issues, https://github.com/Amulet-Team/Amulet-Test-Utils/issues
Classifier: Programming Language :: Python :: 3
Classifier: Operating System :: OS Independent
Requires-Python: >=3.11
License-File: LICENSE
Provides-Extra: dev
Requires-Dist: setuptools>=42; extra == "dev"
Requires-Dist: versioneer; extra == "dev"
Requires-Dist: wheel; extra == "dev"
Requires-Dist: pybind11[global]==2.13.6; extra == "dev"
Requires-Dist: black>=22.3; extra == "dev"
Dynamic: license-file
